pylibimp/__init__.py
pylibimp/__meta__.py
pylibimp/import_hook.py
pylibimp/system.py
pylibimp/__pycache__/__init__.cpython-38.pyc
pylibimp/__pycache__/__meta__.cpython-38.pyc
pylibimp/__pycache__/import_hook.cpython-38.pyc
pylibimp/__pycache__/system.cpython-38.pyc
pylibimp-1.0.1.dist-info/LICENSE
pylibimp-1.0.1.dist-info/METADATA
pylibimp-1.0.1.dist-info/WHEEL
pylibimp-1.0.1.dist-info/top_level.txt
pylibimp-1.0.1.dist-info/RECORD
