Metadata-Version: 2.1
Name: pylibimp
Version: 1.0.1
Summary: Python import utilities
Home-page: https://github.com/justengel/pylibimp
Author: Justin Engel
Author-email: jtengel08@gmail.com
License: MIT
Download-URL: https://github.com/justengel/pylibimp/archive/v1.0.1.tar.gz
Keywords: python import importlib pylibimp pylibimport
Platform: any
Classifier: Programming Language :: Python
Classifier: Programming Language :: Python :: 3
Classifier: Operating System :: OS Independent
